CHANGES.txt
LICENSE.txt
README.txt
bootstrap.py
buildout.cfg
setup.py
src/jquery/__init__.py
src/jquery.layer.egg-info/PKG-INFO
src/jquery.layer.egg-info/SOURCES.txt
src/jquery.layer.egg-info/dependency_links.txt
src/jquery.layer.egg-info/namespace_packages.txt
src/jquery.layer.egg-info/not-zip-safe
src/jquery.layer.egg-info/requires.txt
src/jquery.layer.egg-info/top_level.txt
src/jquery/layer/SETUP.cfg
src/jquery/layer/__init__.py
src/jquery/layer/browser.py
src/jquery/layer/configure.zcml
src/jquery/layer/jquery.layer-configure.zcml
