Metadata-Version: 1.0
Name: jquery.layer
Version: 1.0.0
Summary: Base layers for JQuery functionality
Home-page: http://cheeseshop.python.org/pypi/jquery.layer
Author: Roger Ineichen and the Zope Community
Author-email: zope3-dev@zope.org
License: ZPL 2.1
Keywords: zope3 layer jquery viewlet
Platform: UNKNOWN
Classifier: Development Status :: 5 - Production/Stable
Classifier: Environment :: Web Environment
Classifier: Intended Audience :: Developers
Classifier: License :: OSI Approved :: Zope Public License
Classifier: Programming Language :: Python
Classifier: Natural Language :: English
Classifier: Operating System :: OS Independent
Classifier: Topic :: Internet :: WWW/HTTP
Classifier: Framework :: Zope3
